README.md
setup.cfg
setup.py
cursor/__init__.py
cursor/cursor.py
cursor.egg-info/PKG-INFO
cursor.egg-info/SOURCES.txt
cursor.egg-info/dependency_links.txt
cursor.egg-info/entry_points.txt
cursor.egg-info/top_level.txt