Metadata-Version: 1.0
Name: cursor
Version: 1.3.0
Summary: A small Python package to hide or show the terminal cursor
Home-page: https://github.com/GijsTimmers/cursor
Author: Gijs Timmers
Author-email: timmers.gijs@gmail.com
License: UNKNOWN
Keywords: cursor,terminal,hide,show
Platform: UNKNOWN
